README.md
setup.py
realtrends/__init__.py
realtrends/fetch.py
realtrends/real_fetch.py
realtrends.egg-info/PKG-INFO
realtrends.egg-info/SOURCES.txt
realtrends.egg-info/dependency_links.txt
realtrends.egg-info/not-zip-safe
realtrends.egg-info/requires.txt
realtrends.egg-info/top_level.txt