Metadata-Version: 1.0
Name: realtrends
Version: 1.1.0
Summary: Package to scrape google trends for absolute/real and relative search volumes. Data is presented as a DataFrame.
Home-page: https://github.com/Litharge/realtrends
Author: Robert Chambers
Author-email: 1robertchambers@gmail.com
License: MIT
Platform: UNKNOWN
